page/__init__.py
page/admin.py
page/apps.py
page/models.py
page/shortcode.py
page/tests.py
page/urls.py
page/views.py
page/migrations/0001_initial.py
page/migrations/0002_auto_20181114_0429.py
page/migrations/0003_postcategory_link.py
page/migrations/0004_auto_20181129_0625.py
page/migrations/0005_auto_20181202_1846.py
page/migrations/0006_auto_20181208_2018.py
page/migrations/0007_auto_20181208_2123.py
page/migrations/0008_auto_20181209_2117.py
page/migrations/0009_post_featured.py
page/migrations/0010_auto_20190121_0157.py
page/migrations/0011_popup.py
page/migrations/0012_auto_20190423_1552.py
page/migrations/__init__.py
page/static/ckeditor/ckeditor/plugins/youtube/plugin.js
page/static/ckeditor/ckeditor/plugins/youtube/images/icon-hdpi.png
page/static/ckeditor/ckeditor/plugins/youtube/images/icon.png
page/static/ckeditor/ckeditor/plugins/youtube/lang/ar.js
page/static/ckeditor/ckeditor/plugins/youtube/lang/bg.js
page/static/ckeditor/ckeditor/plugins/youtube/lang/cs.js
page/static/ckeditor/ckeditor/plugins/youtube/lang/de.js
page/static/ckeditor/ckeditor/plugins/youtube/lang/el.js
page/static/ckeditor/ckeditor/plugins/youtube/lang/en.js
page/static/ckeditor/ckeditor/plugins/youtube/lang/es.js
page/static/ckeditor/ckeditor/plugins/youtube/lang/et.js
page/static/ckeditor/ckeditor/plugins/youtube/lang/eu.js
page/static/ckeditor/ckeditor/plugins/youtube/lang/fi.js
page/static/ckeditor/ckeditor/plugins/youtube/lang/fr.js
page/static/ckeditor/ckeditor/plugins/youtube/lang/he.js
page/static/ckeditor/ckeditor/plugins/youtube/lang/hu.js
page/static/ckeditor/ckeditor/plugins/youtube/lang/it.js
page/static/ckeditor/ckeditor/plugins/youtube/lang/ja.js
page/static/ckeditor/ckeditor/plugins/youtube/lang/ko.js
page/static/ckeditor/ckeditor/plugins/youtube/lang/nb.js
page/static/ckeditor/ckeditor/plugins/youtube/lang/nl.js
page/static/ckeditor/ckeditor/plugins/youtube/lang/nn.js
page/static/ckeditor/ckeditor/plugins/youtube/lang/pl.js
django_page-0.0.8.dist-info/LICENSE
django_page-0.0.8.dist-info/METADATA
django_page-0.0.8.dist-info/WHEEL
django_page-0.0.8.dist-info/top_level.txt
django_page-0.0.8.dist-info/RECORD
