Metadata-Version: 2.1
Name: django-page
Version: 0.0.8
Summary: Django korean style simplest CMS
Home-page: https://github.com/bluedisk/django-page
Author: Matthew, lee
Author-email: bluedisk@gmail.com
License: MIT
Keywords: django field widget korean cms
Platform: UNKNOWN
Classifier: Development Status :: 4 - Beta
Classifier: Intended Audience :: Developers
Classifier: License :: OSI Approved :: MIT License
Classifier: Framework :: Django
Classifier: Environment :: Web Environment
Classifier: Topic :: Internet :: WWW/HTTP
Classifier: Topic :: Internet :: WWW/HTTP :: Dynamic Content
Classifier: Programming Language :: Python :: 3.4
Classifier: Programming Language :: Python :: 3.5
Classifier: Programming Language :: Python :: 3.6
Classifier: Programming Language :: Python :: 3.7
Classifier: Programming Language :: Python :: Implementation :: PyPy
Requires-Dist: django
Requires-Dist: django-ckeditor
Requires-Dist: django-reversion
Requires-Dist: django-admin-sortable2
